roocs_utils/__init__.py
roocs_utils/cli.py
roocs_utils/config.py
roocs_utils/exceptions.py
roocs_utils/project_utils.py
roocs_utils/catalog_maker/__init__.py
roocs_utils/catalog_maker/batch.py
roocs_utils/catalog_maker/catalog.py
roocs_utils/catalog_maker/cli.py
roocs_utils/catalog_maker/database.py
roocs_utils/catalog_maker/lotus.py
roocs_utils/catalog_maker/scanner.py
roocs_utils/catalog_maker/task.py
roocs_utils/catalog_maker/utils.py
roocs_utils/etc/roocs.ini
roocs_utils/inventory/__init__.py
roocs_utils/inventory/batch.py
roocs_utils/inventory/cli.py
roocs_utils/inventory/file_lock.py
roocs_utils/inventory/inventory.py
roocs_utils/inventory/lotus.py
roocs_utils/inventory/merge_yaml.py
roocs_utils/inventory/pickle_store.py
roocs_utils/inventory/run_inventory.py
roocs_utils/inventory/scanner.py
roocs_utils/inventory/task.py
roocs_utils/inventory/utils.py
roocs_utils/parameter/__init__.py
roocs_utils/parameter/area_parameter.py
roocs_utils/parameter/base_parameter.py
roocs_utils/parameter/collection_parameter.py
roocs_utils/parameter/dimension_parameter.py
roocs_utils/parameter/level_parameter.py
roocs_utils/parameter/param_utils.py
roocs_utils/parameter/parameterise.py
roocs_utils/parameter/time_components_parameter.py
roocs_utils/parameter/time_parameter.py
roocs_utils/utils/__init__.py
roocs_utils/utils/common.py
roocs_utils/utils/file_utils.py
roocs_utils/utils/time_utils.py
roocs_utils/xarray_utils/__init__.py
roocs_utils/xarray_utils/xarray_utils.py
roocs_utils-0.5.0.dist-info/AUTHORS.rst
roocs_utils-0.5.0.dist-info/LICENSE
roocs_utils-0.5.0.dist-info/METADATA
roocs_utils-0.5.0.dist-info/WHEEL
roocs_utils-0.5.0.dist-info/entry_points.txt
roocs_utils-0.5.0.dist-info/top_level.txt
roocs_utils-0.5.0.dist-info/RECORD
