Metadata-Version: 2.1
Name: roocs-utils
Version: 0.5.0
Summary: A package containing common components for the roocs project
Home-page: https://github.com/roocs/roocs-utils
Author: Elle Smith
Author-email: eleanor.smith@stfc.ac.uk
License: BSD - see LICENSE file in top-level package directory
Keywords: roocs_utils
Platform: UNKNOWN
Classifier: Development Status :: 5 - Production/Stable
Classifier: Environment :: Console
Classifier: Environment :: Web Environment
Classifier: Intended Audience :: End Users/Desktop
Classifier: Intended Audience :: Developers
Classifier: Intended Audience :: System Administrators
Classifier: Intended Audience :: Science/Research
Classifier: License :: OSI Approved :: BSD License
Classifier: Natural Language :: English
Classifier: Operating System :: Microsoft :: Windows
Classifier: Operating System :: POSIX :: Linux
Classifier: Programming Language :: Python
Classifier: Programming Language :: Python :: 3
Classifier: Programming Language :: Python :: 3.5
Classifier: Programming Language :: Python :: 3.6
Classifier: Programming Language :: Python :: 3.7
Classifier: Topic :: Security
Classifier: Topic :: Internet
Classifier: Topic :: Scientific/Engineering
Classifier: Topic :: System :: Distributed Computing
Classifier: Topic :: System :: Systems Administration :: Authentication/Directory
Classifier: Topic :: Software Development :: Libraries :: Python Modules
Requires-Python: >=3.6.0
Requires-Dist: cftime
Requires-Dist: numpy (>=1.16)
Requires-Dist: xarray (>=0.15)
Requires-Dist: dask[complete] (>=2.6)
Requires-Dist: netCDF4 (>=1.4)
Requires-Dist: python-dateutil (>=2.8.1)
Requires-Dist: cf-xarray (>=0.3.1)
Provides-Extra: docs
Requires-Dist: sphinx ; extra == 'docs'
Requires-Dist: sphinx-rtd-theme ; extra == 'docs'
Requires-Dist: nbsphinx ; extra == 'docs'
Requires-Dist: pandoc ; extra == 'docs'
Requires-Dist: ipython ; extra == 'docs'
Requires-Dist: ipykernel ; extra == 'docs'
Requires-Dist: jupyter-client ; extra == 'docs'
Requires-Dist: matplotlib ; extra == 'docs'
